anika/__init__.py
anika/__main__.py
anika/app.py
anika/birthday.py
anika/desktop.py
anika/main.py
anika/data/__init__.py
anika/data/database.py
anika/models/__init__.py
anika/models/task.py
anika/resources/__init__.py
anika/resources/anika.ico
anika/resources/anika_icon.jpg
anika/resources/audio/README.md
anika/resources/audio/birthday_song.mp3
anika/resources/images/anika (1).jpg
anika/resources/images/anika (10).jpg
anika/resources/images/anika (11).jpg
anika/resources/images/anika (12).jpg
anika/resources/images/anika (13).jpg
anika/resources/images/anika (14).jpg
anika/resources/images/anika (15).jpg
anika/resources/images/anika (16).jpg
anika/resources/images/anika (17).jpg
anika/resources/images/anika (18).jpg
anika/resources/images/anika (19).jpg
anika/resources/images/anika (2).jpg
anika/resources/images/anika (20).jpg
anika/resources/images/anika (21).jpg
anika/resources/images/anika (22).jpg
anika/resources/images/anika (23).jpg
anika/resources/images/anika (24).jpg
anika/resources/images/anika (25).jpg
anika/resources/images/anika (26).jpg
anika/resources/images/anika (27).jpg
anika/resources/images/anika (28).jpg
anika/resources/images/anika (29).jpg
anika/resources/images/anika (3).jpg
anika/resources/images/anika (30).jpg
anika/resources/images/anika (31).jpg
anika/resources/images/anika (32).jpg
anika/resources/images/anika (33).jpg
anika/resources/images/anika (34).jpg
anika/resources/images/anika (35).JPG
anika/resources/images/anika (36).jpg
anika/resources/images/anika (37).jpg
anika/resources/images/anika (38).jpg
anika/resources/images/anika (4).jpg
anika/resources/images/anika (5).jpg
anika/resources/images/anika (6).jpg
anika/resources/images/anika (7).jpg
anika/resources/images/anika (8).jpg
anika/resources/images/anika (9).jpg
anika/styles/__init__.py
anika/styles/theme.py
anika/widgets/__init__.py
anika/widgets/calendar.py
anika/widgets/clock.py
anika/widgets/task_dialog.py
anika/widgets/task_list.py
anika_app-1.0.2.dist-info/METADATA
anika_app-1.0.2.dist-info/WHEEL
anika_app-1.0.2.dist-info/entry_points.txt
anika_app-1.0.2.dist-info/top_level.txt
anika_app-1.0.2.dist-info/RECORD
