Metadata-Version: 2.4
Name: anika-app
Version: 1.0.2
Summary: A beautiful cross-platform desktop productivity app - To-Do, Calendar & Clock
Author: Aaryan Choudhary
License: MIT
Project-URL: Homepage, https://github.com/aaryanchoudhary/anika
Classifier: Development Status :: 5 - Production/Stable
Classifier: Environment :: X11 Applications :: Qt
Classifier: Environment :: Win32 (MS Windows)
Classifier: Environment :: MacOS X
Classifier: Intended Audience :: End Users/Desktop
Classifier: License :: OSI Approved :: MIT License
Classifier: Operating System :: OS Independent
Classifier: Programming Language :: Python :: 3
Classifier: Programming Language :: Python :: 3.8
Classifier: Programming Language :: Python :: 3.9
Classifier: Programming Language :: Python :: 3.10
Classifier: Programming Language :: Python :: 3.11
Classifier: Programming Language :: Python :: 3.12
Classifier: Topic :: Office/Business :: Scheduling
Classifier: Topic :: Utilities
Requires-Python: >=3.8
Requires-Dist: PySide6>=6.4.0
Requires-Dist: pygame>=2.5.0
